Some Fancy Title
=====
Code Fragment
```
def add(num1, num2):
    return num1 + num2

print add(1,2)
```
Dissassembled Bytecode
```
python -m dis test.py
  1           0 LOAD_CONST               0 (<code object add at 0x6ffffe2fa30, file "test.py", line 1>)
              3 MAKE_FUNCTION            0
              6 STORE_NAME               0 (add)

  4           9 LOAD_NAME                0 (add)
             12 LOAD_CONST               1 (1)
             15 LOAD_CONST               2 (2)
             18 CALL_FUNCTION            2
             21 PRINT_ITEM
             22 PRINT_NEWLINE
             23 LOAD_CONST               3 (None)
             26 RETURN_VALUE
```
